MANIFEST.in
README.rst
config.py
run.py
setup.py
fab_addon_autodoc/__init__.py
fab_addon_autodoc/autodoc.py
fab_addon_autodoc/manager.py
fab_addon_autodoc/models.py
fab_addon_autodoc/version.py
fab_addon_autodoc/views.py
fab_addon_autodoc.egg-info/PKG-INFO
fab_addon_autodoc.egg-info/SOURCES.txt
fab_addon_autodoc.egg-info/dependency_links.txt
fab_addon_autodoc.egg-info/not-zip-safe
fab_addon_autodoc.egg-info/requires.txt
fab_addon_autodoc.egg-info/top_level.txt
fab_addon_autodoc/static/addon/autodoc/autodoc.css
fab_addon_autodoc/static/addon/autodoc/autodoc.js
fab_addon_autodoc/templates/addon/autodoc/fab_autodoc_list.html
fab_addon_autodoc/translations/pt/LC_MESSAGES/messages.mo
fab_addon_autodoc/translations/pt/LC_MESSAGES/messages.po