Metadata-Version: 1.1
Name: fab-addon-autodoc
Version: 0.1.4
Summary: Wrapped autodo into FAB as an addon
Home-page: https://github.com/dpgaspar/flask-appbuilder/
Author: Shawn Chen
Author-email: UNKNOWN
License: BSD
Platform: any
Classifier: Development Status :: 5 - Production/Stable
Classifier: Environment :: Web Environment
Classifier: Intended Audience :: Developers
Classifier: License :: OSI Approved :: BSD License
Classifier: Operating System :: OS Independent
Classifier: Programming Language :: Python
Classifier: Topic :: Software Development :: Libraries :: Python Modules
